rapbuilder/__init__.py
rapbuilder/config.py
rapbuilder/constant.py
rapbuilder/model.joblib
rapbuilder/rbs_predictor.py
rapbuilder/stem_loop_predictor.py
rapbuilder/utils.py
rapBuilder-0.3.4.dist-info/LICENSE
rapBuilder-0.3.4.dist-info/METADATA
rapBuilder-0.3.4.dist-info/WHEEL
rapBuilder-0.3.4.dist-info/top_level.txt
rapBuilder-0.3.4.dist-info/RECORD
