Metadata-Version: 2.1
Name: rapBuilder
Version: 0.3.4
Summary: find optimal RBS and build pRAP system
Home-page: https://gitlab.igem.org/2023/software-tools/fudan
Author: mistyfield
Author-email: 20301050198@fudan.edu
License: CC BY 4.0
Project-URL: Wiki, https://2023.igem.wiki/fudan/software
Project-URL: Documentation, https://mistyfield.github.io/RAP-Docs/
Platform: linux_x86_64
Requires-Python: >=3.10
License-File: LICENSE
Requires-Dist: ViennaRNA (==2.6.3)
Requires-Dist: tqdm
Requires-Dist: scikit-learn (==1.3.1)
